[
  {
    "name": "",
    "offset": 0,
    "unknownArray": false,
    "type": {
      "array": false,
      "integer": {
        "unsigned": false,
        "size": 4
      }
    },
    "size": 4,
    "unique": false
  },
  {
    "name": "",
    "offset": 4,
    "unknownArray": false,
    "type": {
      "array": false,
      "integer": {
        "unsigned": false,
        "size": 4
      }
    },
    "size": 4,
    "unique": false
  },
  {
    "name": "",
    "offset": 8,
    "unknownArray": false,
    "type": {
      "array": false,
      "integer": {
        "unsigned": false,
        "size": 4
      }
    },
    "size": 4,
    "unique": false
  },
  {
    "name": "",
    "offset": 12,
    "unknownArray": false,
    "type": {
      "array": false,
      "boolean": true
    },
    "size": 1,
    "unique": false
  },
  {
    "name": "",
    "offset": 13,
    "unknownArray": false,
    "type": {
      "array": false,
      "boolean": true
    },
    "size": 1,
    "unique": false
  },
  {
    "name": "",
    "offset": 14,
    "unknownArray": false,
    "type": {
      "array": false,
      "integer": {
        "unsigned": false,
        "size": 4
      }
    },
    "size": 4,
    "unique": false
  },
  {
    "type": {
      "array": false,
      "boolean": true
    },
    "offset": 18,
    "size": 1,
    "unique": false
  }
]