[
  {
    "name": "Id",
    "offset": 0,
    "unknownArray": false,
    "type": {
      "array": false,
      "string": {}
    },
    "size": 8,
    "unique": true
  },
  {
    "name": "BaseItemTypesKeys1",
    "offset": 8,
    "unknownArray": false,
    "type": {
      "array": true,
      "key": {
        "foreign": true,
        "name": "BaseItemTypes"
      }
    },
    "size": 16
  },
  {
    "name": "BaseItemTypesKeys2",
    "offset": 24,
    "unknownArray": false,
    "type": {
      "array": true,
      "key": {
        "foreign": true,
        "name": "BaseItemTypes"
      }
    },
    "size": 16
  },
  {
    "name": "BaseItemTypesKeys3",
    "offset": 40,
    "unknownArray": false,
    "type": {
      "array": true,
      "key": {
        "foreign": true,
        "name": "BaseItemTypes"
      }
    },
    "size": 16
  },
  {
    "name": "BaseItemTypesKeys4",
    "offset": 56,
    "unknownArray": false,
    "type": {
      "array": true,
      "key": {
        "foreign": true,
        "name": "BaseItemTypes"
      }
    },
    "size": 16
  },
  {
    "name": "BaseItemTypesKeys5",
    "offset": 72,
    "unknownArray": false,
    "type": {
      "array": true,
      "key": {
        "foreign": true,
        "name": "BaseItemTypes"
      }
    },
    "size": 16
  },
  {
    "name": "BaseItemTypesKeys6",
    "offset": 88,
    "unknownArray": false,
    "type": {
      "array": true,
      "key": {
        "foreign": true,
        "name": "BaseItemTypes"
      }
    },
    "size": 16
  },
  {
    "name": "BaseItemTypesKeys7",
    "offset": 104,
    "unknownArray": false,
    "type": {
      "array": true,
      "key": {
        "foreign": true,
        "name": "BaseItemTypes"
      }
    },
    "size": 16
  },
  {
    "name": "BaseItemTypesKeys8",
    "offset": 120,
    "unknownArray": false,
    "type": {
      "array": true,
      "key": {
        "foreign": true,
        "name": "BaseItemTypes"
      }
    },
    "size": 16
  },
  {
    "name": "BaseItemTypesKeys9",
    "offset": 136,
    "unknownArray": false,
    "type": {
      "array": true,
      "key": {
        "foreign": true,
        "name": "BaseItemTypes"
      }
    },
    "size": 16
  },
  {
    "name": "BaseItemTypesKeys10",
    "offset": 152,
    "unknownArray": false,
    "type": {
      "array": true,
      "key": {
        "foreign": true,
        "name": "BaseItemTypes"
      }
    },
    "size": 16
  },
  {
    "name": "BaseItemTypesKeys11",
    "offset": 168,
    "unknownArray": false,
    "type": {
      "array": true,
      "key": {
        "foreign": true,
        "name": "BaseItemTypes"
      }
    },
    "size": 16
  },
  {
    "name": "BaseItemTypesKeys12",
    "offset": 184,
    "unknownArray": false,
    "type": {
      "array": true,
      "key": {
        "foreign": true,
        "name": "BaseItemTypes"
      }
    },
    "size": 16
  },
  {
    "name": "WorldAreasKey",
    "offset": 200,
    "unknownArray": false,
    "type": {
      "array": false,
      "key": {
        "foreign": true,
        "name": "WorldAreas"
      }
    },
    "size": 16,
    "unique": true
  },
  {
    "name": "BaseItemTypesKeys13",
    "offset": 216,
    "unknownArray": false,
    "type": {
      "array": true,
      "key": {
        "foreign": true,
        "name": "BaseItemTypes"
      }
    },
    "size": 16
  },
  {
    "name": "BaseItemTypesKeys14",
    "offset": 232,
    "unknownArray": false,
    "type": {
      "array": true,
      "key": {
        "foreign": true,
        "name": "BaseItemTypes"
      }
    },
    "size": 16
  }
]