[
  {
    "name": "GrantedEffect",
    "offset": 0,
    "type": {
      "array": false,
      "key": {
        "foreign": true,
        "name": "GrantedEffects"
      }
    }
  },
  {
    "name": "Level",
    "offset": 16,
    "type": {
      "array": false,
      "integer": {
        "unsigned": false,
        "size": 4
      }
    }
  },
  {
    "name": "PlayerLevelReq",
    "offset": 20,
    "type": {
      "array": false,
      "decimal": {
        "size": 4
      }
    }
  },
  {
    "name": "CostMultiplier",
    "offset": 24,
    "type": {
      "array": false,
      "integer": {
        "unsigned": false,
        "size": 4
      }
    }
  },
  {
    "name": "StoredUses",
    "offset": 28,
    "type": {
      "array": false,
      "integer": {
        "unsigned": false,
        "size": 4
      }
    }
  },
  {
    "name": "Cooldown",
    "offset": 32,
    "type": {
      "array": false,
      "integer": {
        "unsigned": false,
        "size": 4
      }
    }
  },
  {
    "name": "CooldownBypassType",
    "offset": 36,
    "type": {
      "array": false,
      "integer": {
        "unsigned": false,
        "size": 4
      }
    }
  },
  {
    "name": "VaalSouls",
    "offset": 40,
    "type": {
      "array": false,
      "integer": {
        "unsigned": false,
        "size": 4
      }
    }
  },
  {
    "name": "VaalStoredUses",
    "offset": 44,
    "type": {
      "array": false,
      "integer": {
        "unsigned": false,
        "size": 4
      }
    }
  },
  {
    "name": "CooldownGroup",
    "offset": 48,
    "type": {
      "array": false,
      "integer": {
        "unsigned": false,
        "size": 4
      }
    }
  },
  {
    "name": "",
    "offset": 52,
    "type": {
      "array": false,
      "integer": {
        "unsigned": false,
        "size": 4
      }
    }
  },
  {
    "name": "SoulGainPreventionDuration",
    "offset": 56,
    "type": {
      "array": false,
      "integer": {
        "unsigned": false,
        "size": 4
      }
    }
  },
  {
    "name": "AttackSpeedMultiplier",
    "offset": 60,
    "type": {
      "array": false,
      "integer": {
        "unsigned": false,
        "size": 4
      }
    }
  },
  {
    "name": "",
    "offset": 64,
    "type": {
      "array": false,
      "integer": {
        "unsigned": false,
        "size": 4
      }
    }
  },
  {
    "name": "CostAmounts",
    "offset": 68,
    "type": {
      "array": true,
      "integer": {
        "unsigned": false,
        "size": 4
      }
    }
  },
  {
    "name": "CostTypes",
    "offset": 84,
    "type": {
      "array": true,
      "key": {
        "foreign": true,
        "name": "CostTypes"
      }
    }
  },
  {
    "name": "ManaReservationFlat",
    "offset": 100,
    "type": {
      "array": false,
      "integer": {
        "unsigned": false,
        "size": 4
      }
    }
  },
  {
    "name": "ManaReservationPercent",
    "offset": 104,
    "type": {
      "array": false,
      "integer": {
        "unsigned": false,
        "size": 4
      }
    }
  },
  {
    "name": "LifeReservationFlat",
    "offset": 108,
    "type": {
      "array": false,
      "integer": {
        "unsigned": false,
        "size": 4
      }
    }
  },
  {
    "name": "LifeReservationPercent",
    "offset": 112,
    "type": {
      "array": false,
      "integer": {
        "unsigned": false,
        "size": 4
      }
    }
  },
  {
    "name": "AttackTime",
    "offset": 116,
    "type": {
      "array": false,
      "integer": {
        "unsigned": false,
        "size": 4
      }
    }
  }
]