[
  {
    "name": "HeistJobsKey",
    "offset": 0,
    "type": {
      "array": false,
      "key": {
        "foreign": true,
        "name": "HeistJobs"
      }
    }
  },
  {
    "name": "Tier",
    "offset": 16,
    "type": {
      "array": false,
      "integer": {
        "unsigned": false,
        "size": 4
      }
    }
  },
  {
    "name": "Experience",
    "offset": 20,
    "type": {
      "array": false,
      "integer": {
        "unsigned": false,
        "size": 4
      }
    }
  },
  {
    "name": "MinLevel",
    "offset": 24,
    "type": {
      "array": false,
      "integer": {
        "unsigned": false,
        "size": 4
      }
    }
  },
  {
    "name": "AchievementItemsKey",
    "offset": 28,
    "type": {
      "array": true,
      "key": {
        "foreign": true,
        "name": "AchievementItems"
      }
    }
  }
]