[
  {
    "name": "AchievementItemsKey",
    "offset": 0,
    "unknownArray": false,
    "unique": true,
    "type": {
      "array": false,
      "key": {
        "foreign": true,
        "name": "AchievementItems"
      }
    },
    "size": 16
  },
  {
    "name": "BaseItemTypesKey",
    "offset": 16,
    "unknownArray": false,
    "unique": true,
    "type": {
      "array": false,
      "key": {
        "foreign": true,
        "name": "BaseItemTypes"
      }
    },
    "size": 16
  },
  {
    "name": "Message",
    "offset": 32,
    "unknownArray": false,
    "unique": true,
    "type": {
      "array": false,
      "string": {}
    },
    "size": 8,
    "localized": true
  },
  {
    "name": "Id",
    "offset": 40,
    "unknownArray": false,
    "unique": true,
    "type": {
      "array": false,
      "string": {}
    },
    "size": 8
  }
]